pooldb/__init__.py
pooldb/backends/__init__.py
pooldb/backends/mysql/__init__.py
pooldb/backends/mysql/base.py
pooldb/backends/postgresql/__init__.py
pooldb/backends/postgresql/base.py
django_pooldb-1.2.dist-info/LICENSE
django_pooldb-1.2.dist-info/METADATA
django_pooldb-1.2.dist-info/WHEEL
django_pooldb-1.2.dist-info/top_level.txt
django_pooldb-1.2.dist-info/RECORD
