Metadata-Version: 2.1
Name: django-pooldb
Version: 1.2
Summary: 基于DBUtils.PooledDB封装的Django数据库连接引擎
Home-page: https://github.com/liangalien/django-pooldb
Author: shiqiangliang
Author-email: lsq54264@vip.qq.com
License: MIT
Keywords: django db pool,django mysql pool,django postgres pool
Platform: UNKNOWN
Classifier: Programming Language :: Python :: 3
Classifier: License :: OSI Approved :: MIT License
Classifier: Operating System :: OS Independent
Requires-Python: >=3.6,<3.11
Requires-Dist: django (==3.2.18)
Requires-Dist: DBUtils
Requires-Dist: pymysql
Requires-Dist: psycopg2
